burst_interface_c.abi3.so
burst_interface_c.pyi
burst_link_protocol/__init__.py
burst_link_protocol/main.py
burst_link_protocol/serial_burst_interface.py
burst_link_protocol-1.1.5.dist-info/METADATA
burst_link_protocol-1.1.5.dist-info/WHEEL
burst_link_protocol-1.1.5.dist-info/RECORD
burst_link_protocol-1.1.5.dist-info/licenses/LICENSE
