Metadata-Version: 2.4
Name: burst-link-protocol
Version: 1.1.5
Summary: Binary Utility for Reliable Stream Transfer (BURST) is a library for encoding and decoding binary data streams into and from a byte stream.
Author-Email: Floris vernieuwe <floris@vernieuwe.eu>
License-File: LICENSE
Project-URL: Repository, https://github.com/Florioo/burst-link-protocol
Requires-Python: <4.0,>=3.10
Requires-Dist: cobs<2.0.0,>=1.2.1
Requires-Dist: numpy<3.0.0,>=2.2.3
Requires-Dist: crc<8.0.0,>=7.1.0
Requires-Dist: pytest<9.0.0,>=8.3.4
Requires-Dist: pytest-cov<7.0.0,>=6.0.0
Requires-Dist: pytest-benchmark<6.0.0,>=5.1.0
Requires-Dist: scikit-build-core>=0.10.7
Requires-Dist: nanobind>=2.5.0
Requires-Dist: pyserial>=3.5
Requires-Dist: janus>=2.0.0
Provides-Extra: dev
Requires-Dist: scikit-build-core[pyproject]<0.11.0,>=0.10.7; extra == "dev"
Requires-Dist: nanobind<3.0.0,>=2.5.0; extra == "dev"
Requires-Dist: pytest<9.0.0,>=8.3.4; extra == "dev"
Requires-Dist: pytest-cov<7.0.0,>=6.0.0; extra == "dev"
Requires-Dist: pytest-benchmark<6.0.0,>=5.1.0; extra == "dev"
